{
	"info": {
		"_postman_id": "b81bb783-992f-4dd5-aa0d-1ab6ec367cb3",
		"name": "Sem5",
		"schema": "https://schema.getpostman.com/json/collection/v2.0.0/collection.json",
		"_exporter_id": "29440876"
	},
	"item": [
		{
			"name": "Список всех задач",
			"request": {
				"method": "GET",
				"header": [],
				"url": "localhost:8081/api/tasks"
			},
			"response": []
		},
		{
			"name": "Добавление задачи",
			"request": {
				"method": "POST",
				"header": [],
				"body": {
					"mode": "raw",
					"raw": "{\r\n    \"description\" : \"Some task 2\"\r\n}",
					"options": {
						"raw": {
							"language": "json"
						}
					}
				},
				"url": "localhost:8081/api/addTask"
			},
			"response": []
		},
		{
			"name": "Просмотр задач по статусу",
			"request": {
				"method": "GET",
				"header": [],
				"url": "localhost:8081/api/status/NOT_STARTED"
			},
			"response": []
		},
		{
			"name": "Обновление статуса задачи",
			"request": {
				"method": "PUT",
				"header": [],
				"body": {
					"mode": "raw",
					"raw": "{\r\n    \"taskStatus\": \"IN_PROGRESS\"\r\n}",
					"options": {
						"raw": {
							"language": "json"
						}
					}
				},
				"url": "localhost:8081/api/1"
			},
			"response": []
		},
		{
			"name": "Удаление задачи",
			"request": {
				"method": "DELETE",
				"header": [],
				"url": "localhost:8081/api/2"
			},
			"response": []
		}
	]
}